[
  {
    "id": 800,
    "title": "Os Números Complexos - Aula 01 - Variável Complexa para Engenharia (FGA/UnB)",
    "embedUrl": "https://www.youtube.com/embed/_k1arnt1I5s",
    "duration": 3546
  },
  {
    "id": 801,
    "title": "Raízes de Números Complexos - Aula 02 - Variável Complexa para Engenharia (FGA/UnB)",
    "embedUrl": "https://www.youtube.com/embed/_6SjEzJ8j68",
    "duration": 3500
  },
  {
    "id": 802,
    "title": "Funções de Variável Complexa - Aula 03 - Variável Complexa para Engenharia (FGA/UnB)",
    "embedUrl": "https://www.youtube.com/embed/SbPm4xLx_aQ",
    "duration": 3310
  },
  {
    "id": 803,
    "title": "Limites - Aula 04 - Variável Complexa para Engenharia (FGA/UnB)",
    "embedUrl": "https://www.youtube.com/embed/G3W3xIdKi0E",
    "duration": 2016
  },
  {
    "id": 804,
    "title": "Derivadas - Aula 05 - Variável Complexa para Engenharia (FGA/UnB)",
    "embedUrl": "https://www.youtube.com/embed/dt5nCJCXgOY",
    "duration": 3250
  },
  {
    "id": 805,
    "title": "Analiticidade - Aula 06 - Variável Complexa para Engenharia (FGA/UnB)",
    "embedUrl": "https://www.youtube.com/embed/6Ccfp4VbKUI",
    "duration": 2585
  },
  {
    "id": 806,
    "title": "Equações de Cauchy-Riemann - Aula 07 - Variável Complexa para Engenharia (FGA/UnB)",
    "embedUrl": "https://www.youtube.com/embed/tPExevykzBE",
    "duration": 4019
  },
  {
    "id": 807,
    "title": "Funções Elementares (Parte 1) - Aula 08 - Variável Complexa para Engenharia (FGA/UnB)",
    "embedUrl": "https://www.youtube.com/embed/9NmxxVoD_A8",
    "duration": 3515
  },
  {
    "id": 808,
    "title": "Funções Elementares (Parte 2) - Aula 09 - Variável Complexa para Engenharia (FGA/UnB)",
    "embedUrl": "https://www.youtube.com/embed/wbFsmCgpO3A",
    "duration": 3626
  },
  {
    "id": 809,
    "title": "Integração Complexa - Aula 10 - Variável Complexa para Engenharia (FGA/UnB)",
    "embedUrl": "https://www.youtube.com/embed/-OmDio0gYZY",
    "duration": 3885
  },
  {
    "id": 810,
    "title": "Teorema de Cauchy-Goursat - Aula 11 - Variável Complexa para Engenharia (FGA/UnB)",
    "embedUrl": "https://www.youtube.com/embed/vX_Tm_Tacy4",
    "duration": 3810
  },
  {
    "id": 811,
    "title": "Fórmula Integral de Cauchy - Aula 12 - Variável Complexa para Engenharia (FGA/UnB)",
    "embedUrl": "https://www.youtube.com/embed/r22Sghwn4E8",
    "duration": 3855
  },
  {
    "id": 812,
    "title": "Sequências e Séries - Aula 13 - Variável Complexa para Engenharia (FGA/UnB)",
    "embedUrl": "https://www.youtube.com/embed/RC7o0_P7TdU",
    "duration": 4030
  },
  {
    "id": 813,
    "title": "Série de Taylor - Aula 14 - Variável Complexa para Engenharia (FGA/UnB)",
    "embedUrl": "https://www.youtube.com/embed/_0uOEi8kndA",
    "duration": 4486
  },
  {
    "id": 814,
    "title": "Série de Laurent - Aula 15 - Variável Complexa para Engenharia (FGA/UnB)",
    "embedUrl": "https://www.youtube.com/embed/e7MAukbZHyk",
    "duration": 3869
  },
  {
    "id": 815,
    "title": "Singularides e Pólos - Aula 16 - Variável Complexa para Engenharia (FGA/UnB)",
    "embedUrl": "https://www.youtube.com/embed/SobeuJJ8Ihc",
    "duration": 3003
  },
  {
    "id": 816,
    "title": "Resíduos e Teorema dos Resíduos - Aula 17 - Variável Complexa para Engenharia (FGA/UnB)",
    "embedUrl": "https://www.youtube.com/embed/LKQnzMGJ1yw",
    "duration": 3855
  },
  {
    "id": 817,
    "title": "Integrais Trigonométricas Reais - Aula 18 - Variável Complexa para Engenharia (FGA/UnB)",
    "embedUrl": "https://www.youtube.com/embed/1ZLgKi0VVHI",
    "duration": 2684
  },
  {
    "id": 818,
    "title": "Integrais Impróprias Reais - Aula 19 - Variável Complexa para Engenharia (FGA/UnB)",
    "embedUrl": "https://www.youtube.com/embed/r3KkRLj8cd0",
    "duration": 3056
  },
  {
    "id": 819,
    "title": "Soma de Séries Infinitas - Aula 20 - Variável Complexa para Engenharia (FGA/UnB)",
    "embedUrl": "https://www.youtube.com/embed/vtzBjHFfGlY",
    "duration": 3551
  },
  {
    "id": 820,
    "title": "Invertendo a Transformada de Laplace - Aula 21 - Variável Complexa para Engenharia (FGA/UnB)",
    "embedUrl": "https://www.youtube.com/embed/Bh2wx6TGh_M",
    "duration": 3920
  }
]